{
  "last_node_id": 15,
  "last_link_id": 26,
  "nodes": [
    {
      "id": 1,
      "type": "CheckpointLoaderSimple",
      "pos": [
        309.0357971191406,
        385.0704345703125
      ],
      "size": [
        315,
        98
      ],
      "flags": {},
      "order": 0,
      "mode": 0,
      "inputs": [],
      "outputs": [
        {
          "name": "MODEL",
          "type": "MODEL",
          "links": [
            20
          ],
          "slot_index": 0
        },
        {
          "name": "CLIP",
          "type": "CLIP",
          "links": [
            1,
            2
          ],
          "slot_index": 1
        },
        {
          "name": "VAE",
          "type": "VAE",
          "links": [
            9
          ],
          "slot_index": 2
        }
      ],
      "properties": {
        "Node name for S&R": "CheckpointLoaderSimple"
      },
      "widgets_values": [
        "sdxl/juggernautXL_v9Rundiffusionphoto2.safetensors"
      ]
    },
    {
      "id": 12,
      "type": "LoadImage",
      "pos": [
        305.1360168457031,
        15.870855331420898
      ],
      "size": [
        315,
        314
      ],
      "flags": {},
      "order": 1,
      "mode": 0,
      "inputs": [],
      "outputs": [
        {
          "name": "IMAGE",
          "type": "IMAGE",
          "links": [
            23
          ]
        },
        {
          "name": "MASK",
          "type": "MASK",
          "links": null
        }
      ],
      "properties": {
        "Node name for S&R": "LoadImage"
      },
      "widgets_values": [
        "Screenshot 2025-03-08 004324.png",
        "image"
      ]
    },
    {
      "id": 11,
      "type": "ApplyInstantID",
      "pos": [
        1094.693603515625,
        6.8857879638671875
      ],
      "size": [
        315,
        266
      ],
      "flags": {},
      "order": 8,
      "mode": 0,
      "inputs": [
        {
          "name": "instantid",
          "type": "INSTANTID",
          "link": 26
        },
        {
          "name": "insightface",
          "type": "FACEANALYSIS",
          "link": 25
        },
        {
          "name": "control_net",
          "type": "CONTROL_NET",
          "link": 24
        },
        {
          "name": "image",
          "type": "IMAGE",
          "link": 23
        },
        {
          "name": "model",
          "type": "MODEL",
          "link": 20
        },
        {
          "name": "positive",
          "type": "CONDITIONING",
          "link": 21
        },
        {
          "name": "negative",
          "type": "CONDITIONING",
          "link": 22
        },
        {
          "name": "image_kps",
          "type": "IMAGE",
          "link": null,
          "shape": 7
        },
        {
          "name": "mask",
          "type": "MASK",
          "link": null,
          "shape": 7
        }
      ],
      "outputs": [
        {
          "name": "MODEL",
          "type": "MODEL",
          "links": [
            19
          ],
          "slot_index": 0
        },
        {
          "name": "positive",
          "type": "CONDITIONING",
          "links": [
            17
          ],
          "slot_index": 1
        },
        {
          "name": "negative",
          "type": "CONDITIONING",
          "links": [
            18
          ],
          "slot_index": 2
        }
      ],
      "properties": {
        "Node name for S&R": "ApplyInstantID"
      },
      "widgets_values": [
        0.8,
        0,
        1
      ]
    },
    {
      "id": 7,
      "type": "SaveImage",
      "pos": [
        1452.328125,
        237.6135711669922
      ],
      "size": [
        315,
        270
      ],
      "flags": {},
      "order": 11,
      "mode": 0,
      "inputs": [
        {
          "name": "images",
          "type": "IMAGE",
          "link": 7
        }
      ],
      "outputs": [],
      "properties": {
        "Node name for S&R": "SaveImage"
      },
      "widgets_values": [
        "ComfyUI"
      ]
    },
    {
      "id": 2,
      "type": "CLIPTextEncode",
      "pos": [
        662.0037841796875,
        24.534170150756836
      ],
      "size": [
        400,
        200
      ],
      "flags": {},
      "order": 6,
      "mode": 0,
      "inputs": [
        {
          "name": "clip",
          "type": "CLIP",
          "link": 1
        }
      ],
      "outputs": [
        {
          "name": "CONDITIONING",
          "type": "CONDITIONING",
          "links": [
            21
          ],
          "slot_index": 0
        }
      ],
      "properties": {
        "Node name for S&R": "CLIPTextEncode"
      },
      "widgets_values": [
        "headshot\n"
      ]
    },
    {
      "id": 13,
      "type": "ControlNetLoader",
      "pos": [
        357.2965087890625,
        -89.90570831298828
      ],
      "size": [
        315,
        58
      ],
      "flags": {},
      "order": 2,
      "mode": 0,
      "inputs": [],
      "outputs": [
        {
          "name": "CONTROL_NET",
          "type": "CONTROL_NET",
          "links": [
            24
          ]
        }
      ],
      "properties": {
        "Node name for S&R": "ControlNetLoader"
      },
      "widgets_values": [
        "SDXL/instantid/diffusion_pytorch_model.safetensors"
      ]
    },
    {
      "id": 14,
      "type": "InstantIDFaceAnalysis",
      "pos": [
        1058.03271484375,
        -102.51988220214844
      ],
      "size": [
        315,
        58
      ],
      "flags": {},
      "order": 3,
      "mode": 0,
      "inputs": [],
      "outputs": [
        {
          "name": "FACEANALYSIS",
          "type": "FACEANALYSIS",
          "links": [
            25
          ]
        }
      ],
      "properties": {
        "Node name for S&R": "InstantIDFaceAnalysis"
      },
      "widgets_values": [
        "CUDA"
      ]
    },
    {
      "id": 15,
      "type": "InstantIDModelLoader",
      "pos": [
        701.6417236328125,
        -96.10311889648438
      ],
      "size": [
        315,
        58
      ],
      "flags": {},
      "order": 4,
      "mode": 0,
      "inputs": [],
      "outputs": [
        {
          "name": "INSTANTID",
          "type": "INSTANTID",
          "links": [
            26
          ]
        }
      ],
      "properties": {
        "Node name for S&R": "InstantIDModelLoader"
      },
      "widgets_values": [
        "SDXL/ip-adapter.bin"
      ]
    },
    {
      "id": 6,
      "type": "VAEDecode",
      "pos": [
        1450.670654296875,
        142.7979278564453
      ],
      "size": [
        210,
        46
      ],
      "flags": {},
      "order": 10,
      "mode": 0,
      "inputs": [
        {
          "name": "samples",
          "type": "LATENT",
          "link": 6
        },
        {
          "name": "vae",
          "type": "VAE",
          "link": 9
        }
      ],
      "outputs": [
        {
          "name": "IMAGE",
          "type": "IMAGE",
          "links": [
            7
          ],
          "slot_index": 0
        }
      ],
      "properties": {
        "Node name for S&R": "VAEDecode"
      },
      "widgets_values": []
    },
    {
      "id": 5,
      "type": "KSampler",
      "pos": [
        1095.9619140625,
        329.11700439453125
      ],
      "size": [
        315,
        262
      ],
      "flags": {},
      "order": 9,
      "mode": 0,
      "inputs": [
        {
          "name": "model",
          "type": "MODEL",
          "link": 19
        },
        {
          "name": "positive",
          "type": "CONDITIONING",
          "link": 17
        },
        {
          "name": "negative",
          "type": "CONDITIONING",
          "link": 18
        },
        {
          "name": "latent_image",
          "type": "LATENT",
          "link": 5
        }
      ],
      "outputs": [
        {
          "name": "LATENT",
          "type": "LATENT",
          "links": [
            6
          ],
          "slot_index": 0
        }
      ],
      "properties": {
        "Node name for S&R": "KSampler"
      },
      "widgets_values": [
        828159400811010,
        "randomize",
        20,
        2,
        "euler",
        "normal",
        1
      ]
    },
    {
      "id": 3,
      "type": "CLIPTextEncode",
      "pos": [
        662.8343505859375,
        269.6448974609375
      ],
      "size": [
        400,
        200
      ],
      "flags": {},
      "order": 7,
      "mode": 0,
      "inputs": [
        {
          "name": "clip",
          "type": "CLIP",
          "link": 2
        }
      ],
      "outputs": [
        {
          "name": "CONDITIONING",
          "type": "CONDITIONING",
          "links": [
            22
          ],
          "slot_index": 0
        }
      ],
      "properties": {
        "Node name for S&R": "CLIPTextEncode"
      },
      "widgets_values": [
        "nsfw"
      ]
    },
    {
      "id": 4,
      "type": "EmptyLatentImage",
      "pos": [
        728.4788818359375,
        520.9046020507812
      ],
      "size": [
        315,
        106
      ],
      "flags": {},
      "order": 5,
      "mode": 0,
      "inputs": [],
      "outputs": [
        {
          "name": "LATENT",
          "type": "LATENT",
          "links": [
            5
          ],
          "slot_index": 0
        }
      ],
      "properties": {
        "Node name for S&R": "EmptyLatentImage"
      },
      "widgets_values": [
        1024,
        1024,
        1
      ]
    }
  ],
  "links": [
    [
      1,
      1,
      1,
      2,
      0,
      "CLIP"
    ],
    [
      2,
      1,
      1,
      3,
      0,
      "CLIP"
    ],
    [
      5,
      4,
      0,
      5,
      3,
      "LATENT"
    ],
    [
      6,
      5,
      0,
      6,
      0,
      "LATENT"
    ],
    [
      7,
      6,
      0,
      7,
      0,
      "IMAGE"
    ],
    [
      9,
      1,
      2,
      6,
      1,
      "VAE"
    ],
    [
      17,
      11,
      1,
      5,
      1,
      "CONDITIONING"
    ],
    [
      18,
      11,
      2,
      5,
      2,
      "CONDITIONING"
    ],
    [
      19,
      11,
      0,
      5,
      0,
      "MODEL"
    ],
    [
      20,
      1,
      0,
      11,
      4,
      "MODEL"
    ],
    [
      21,
      2,
      0,
      11,
      5,
      "CONDITIONING"
    ],
    [
      22,
      3,
      0,
      11,
      6,
      "CONDITIONING"
    ],
    [
      23,
      12,
      0,
      11,
      3,
      "IMAGE"
    ],
    [
      24,
      13,
      0,
      11,
      2,
      "CONTROL_NET"
    ],
    [
      25,
      14,
      0,
      11,
      1,
      "FACEANALYSIS"
    ],
    [
      26,
      15,
      0,
      11,
      0,
      "INSTANTID"
    ]
  ],
  "groups": [],
  "config": {},
  "extra": {
    "ds": {
      "scale": 0.6934334949441378,
      "offset": [
        -152.87578639745396,
        199.42113203155998
      ]
    },
    "VHS_latentpreview": false,
    "VHS_latentpreviewrate": 0
  },
  "version": 0.4
}